[
    {
        "gamesPlayed": "11",
        "talents": [
            {
                "desc": "Smite deals 25% more damage to Heroes.",
                "img": "//d1i1jxrdh2kvwy.cloudfront.net/Images/Talents/PurgeEvil.png",
                "lvl": 1,
                "name": "Purge Evil"
            },
            {
                "desc": "Increases regeneration effects and all healing received by 30%.",
                "img": "//d1i1jxrdh2kvwy.cloudfront.net/Images/Talents/AmplifiedHealing.png",
                "lvl": 4,
                "name": "Amplified Healing"
            },
            {
                "desc": "Basic Attacks reduce Ability cooldowns by 0.5 seconds.",
                "img": "//d1i1jxrdh2kvwy.cloudfront.net/Images/Talents/BattleMomentum.png",
                "lvl": 7,
                "name": "Battle Momentum"
            },
            {
                "desc": "While channeling, make all nearby allied Heroes, excluding you, invulnerable. Lasts 3 seconds.",
                "img": "//d1i1jxrdh2kvwy.cloudfront.net/Images/Talents/Sanctification.png",
                "lvl": 10,
                "name": "Sanctification"
            },
            {
                "desc": "Enemies that attack you while shielded have their Attack Speed slowed by 50% and Movement Speed slowed by 50% for 2 seconds.",
                "img": "//d1i1jxrdh2kvwy.cloudfront.net/Images/Talents/ImposingWill.png",
                "lvl": 13,
                "name": "Imposing Will"
            },
            {
                "desc": "Create a ring that blocks enemies from entering the area teleported to using El'Druin's Might.",
                "img": "//d1i1jxrdh2kvwy.cloudfront.net/Images/Talents/HolyGround.png",
                "lvl": 16,
                "name": "Holy Ground"
            },
            {
                "desc": "Activate to reduce damage taken by 75% for 4 seconds.",
                "img": "//d1i1jxrdh2kvwy.cloudfront.net/Images/Talents/HardenedShield.png",
                "lvl": 20,
                "name": "Hardened Shield"
            }
        ],
        "winPercent": "90.9 %"
    },
    {
        "gamesPlayed": "14",
        "talents": [
            {
                "desc": "Smite deals 25% more damage to Heroes.",
                "img": "//d1i1jxrdh2kvwy.cloudfront.net/Images/Talents/PurgeEvil.png",
                "lvl": 1,
                "name": "Purge Evil"
            },
            {
                "desc": "Increases regeneration effects and all healing received by 30%.",
                "img": "//d1i1jxrdh2kvwy.cloudfront.net/Images/Talents/AmplifiedHealing.png",
                "lvl": 4,
                "name": "Amplified Healing"
            },
            {
                "desc": "Basic Attacks reduce Ability cooldowns by 0.5 seconds.",
                "img": "//d1i1jxrdh2kvwy.cloudfront.net/Images/Talents/BattleMomentum.png",
                "lvl": 7,
                "name": "Battle Momentum"
            },
            {
                "desc": "While channeling, make all nearby allied Heroes, excluding you, invulnerable. Lasts 3 seconds.",
                "img": "//d1i1jxrdh2kvwy.cloudfront.net/Images/Talents/Sanctification.png",
                "lvl": 10,
                "name": "Sanctification"
            },
            {
                "desc": "Enemies that attack you while shielded have their Attack Speed slowed by 50% and Movement Speed slowed by 50% for 2 seconds.",
                "img": "//d1i1jxrdh2kvwy.cloudfront.net/Images/Talents/ImposingWill.png",
                "lvl": 13,
                "name": "Imposing Will"
            },
            {
                "desc": "Activate to deal 10% of target enemy Hero's Max Health and heal for twice that amount.",
                "img": "//d1i1jxrdh2kvwy.cloudfront.net/Images/Talents/BloodforBlood.png",
                "lvl": 16,
                "name": "Blood for Blood"
            },
            {
                "desc": "Activate to reduce damage taken by 75% for 4 seconds.",
                "img": "//d1i1jxrdh2kvwy.cloudfront.net/Images/Talents/HardenedShield.png",
                "lvl": 20,
                "name": "Hardened Shield"
            }
        ],
        "winPercent": "85.7 %"
    },
    {
        "gamesPlayed": "16",
        "talents": [
            {
                "desc": "Collecting Regeneration Globes permanently increases Health Regeneration by 1.5 per second.",
                "img": "//d1i1jxrdh2kvwy.cloudfront.net/Images/Talents/RegenerationMaster.png",
                "lvl": 1,
                "name": "Regeneration Master"
            },
            {
                "desc": "Increases regeneration effects and all healing received by 30%.",
                "img": "//d1i1jxrdh2kvwy.cloudfront.net/Images/Talents/AmplifiedHealing.png",
                "lvl": 4,
                "name": "Amplified Healing"
            },
            {
                "desc": "Basic Attacks reduce Ability cooldowns by 0.5 seconds.",
                "img": "//d1i1jxrdh2kvwy.cloudfront.net/Images/Talents/BattleMomentum.png",
                "lvl": 7,
                "name": "Battle Momentum"
            },
            {
                "desc": "Charge target enemy Hero, dealing 60 (+8 per level) damage and stunning them for 1.5 seconds. While charging, nearby enemies are knocked back and take 30 (+4 per level) damage.",
                "img": "//d1i1jxrdh2kvwy.cloudfront.net/Images/Talents/Judgment.png",
                "lvl": 10,
                "name": "Judgment"
            },
            {
                "desc": "Enemies that attack you while shielded grant 60 (+12 per level) Health over 3 seconds.",
                "img": "//d1i1jxrdh2kvwy.cloudfront.net/Images/Talents/AngelicAbsorption.png",
                "lvl": 13,
                "name": "Angelic Absorption"
            },
            {
                "desc": "Activate to deal 10% of target enemy Hero's Max Health and heal for twice that amount.",
                "img": "//d1i1jxrdh2kvwy.cloudfront.net/Images/Talents/BloodforBlood.png",
                "lvl": 16,
                "name": "Blood for Blood"
            },
            {
                "desc": "Activate to reduce damage taken by 75% for 4 seconds.",
                "img": "//d1i1jxrdh2kvwy.cloudfront.net/Images/Talents/HardenedShield.png",
                "lvl": 20,
                "name": "Hardened Shield"
            }
        ],
        "winPercent": "75.0 %"
    },
    {
        "gamesPlayed": "40",
        "talents": [
            {
                "desc": "Smite deals 25% more damage to Heroes.",
                "img": "//d1i1jxrdh2kvwy.cloudfront.net/Images/Talents/PurgeEvil.png",
                "lvl": 1,
                "name": "Purge Evil"
            },
            {
                "desc": "Increases regeneration effects and all healing received by 30%.",
                "img": "//d1i1jxrdh2kvwy.cloudfront.net/Images/Talents/AmplifiedHealing.png",
                "lvl": 4,
                "name": "Amplified Healing"
            },
            {
                "desc": "Basic Attacks reduce Ability cooldowns by 0.5 seconds.",
                "img": "//d1i1jxrdh2kvwy.cloudfront.net/Images/Talents/BattleMomentum.png",
                "lvl": 7,
                "name": "Battle Momentum"
            },
            {
                "desc": "Charge target enemy Hero, dealing 60 (+8 per level) damage and stunning them for 1.5 seconds. While charging, nearby enemies are knocked back and take 30 (+4 per level) damage.",
                "img": "//d1i1jxrdh2kvwy.cloudfront.net/Images/Talents/Judgment.png",
                "lvl": 10,
                "name": "Judgment"
            },
            {
                "desc": "Enemies that attack you while shielded have their Attack Speed slowed by 50% and Movement Speed slowed by 50% for 2 seconds.",
                "img": "//d1i1jxrdh2kvwy.cloudfront.net/Images/Talents/ImposingWill.png",
                "lvl": 13,
                "name": "Imposing Will"
            },
            {
                "desc": "Activate to deal 10% of target enemy Hero's Max Health and heal for twice that amount.",
                "img": "//d1i1jxrdh2kvwy.cloudfront.net/Images/Talents/BloodforBlood.png",
                "lvl": 16,
                "name": "Blood for Blood"
            },
            {
                "desc": "Activate to reduce damage taken by 75% for 4 seconds.",
                "img": "//d1i1jxrdh2kvwy.cloudfront.net/Images/Talents/HardenedShield.png",
                "lvl": 20,
                "name": "Hardened Shield"
            }
        ],
        "winPercent": "72.5 %"
    },
    {
        "gamesPlayed": "36",
        "talents": [
            {
                "desc": "Collecting Regeneration Globes permanently increases Health Regeneration by 1.5 per second.",
                "img": "//d1i1jxrdh2kvwy.cloudfront.net/Images/Talents/RegenerationMaster.png",
                "lvl": 1,
                "name": "Regeneration Master"
            },
            {
                "desc": "Increases regeneration effects and all healing received by 30%.",
                "img": "//d1i1jxrdh2kvwy.cloudfront.net/Images/Talents/AmplifiedHealing.png",
                "lvl": 4,
                "name": "Amplified Healing"
            },
            {
                "desc": "Basic Attacks reduce Ability cooldowns by 0.5 seconds.",
                "img": "//d1i1jxrdh2kvwy.cloudfront.net/Images/Talents/BattleMomentum.png",
                "lvl": 7,
                "name": "Battle Momentum"
            },
            {
                "desc": "Charge target enemy Hero, dealing 60 (+8 per level) damage and stunning them for 1.5 seconds. While charging, nearby enemies are knocked back and take 30 (+4 per level) damage.",
                "img": "//d1i1jxrdh2kvwy.cloudfront.net/Images/Talents/Judgment.png",
                "lvl": 10,
                "name": "Judgment"
            },
            {
                "desc": "Enemies that attack you while shielded have their Attack Speed slowed by 50% and Movement Speed slowed by 50% for 2 seconds.",
                "img": "//d1i1jxrdh2kvwy.cloudfront.net/Images/Talents/ImposingWill.png",
                "lvl": 13,
                "name": "Imposing Will"
            },
            {
                "desc": "Activate to deal 10% of target enemy Hero's Max Health and heal for twice that amount.",
                "img": "//d1i1jxrdh2kvwy.cloudfront.net/Images/Talents/BloodforBlood.png",
                "lvl": 16,
                "name": "Blood for Blood"
            },
            {
                "desc": "Activate to reduce damage taken by 75% for 4 seconds.",
                "img": "//d1i1jxrdh2kvwy.cloudfront.net/Images/Talents/HardenedShield.png",
                "lvl": 20,
                "name": "Hardened Shield"
            }
        ],
        "winPercent": "69.4 %"
    },
    {
        "gamesPlayed": "13",
        "talents": [
            {
                "desc": "Collecting Regeneration Globes permanently increases Health Regeneration by 1.5 per second.",
                "img": "//d1i1jxrdh2kvwy.cloudfront.net/Images/Talents/RegenerationMaster.png",
                "lvl": 1,
                "name": "Regeneration Master"
            },
            {
                "desc": "Increases regeneration effects and all healing received by 30%.",
                "img": "//d1i1jxrdh2kvwy.cloudfront.net/Images/Talents/AmplifiedHealing.png",
                "lvl": 4,
                "name": "Amplified Healing"
            },
            {
                "desc": "Basic Attacks reduce Ability cooldowns by 0.5 seconds.",
                "img": "//d1i1jxrdh2kvwy.cloudfront.net/Images/Talents/BattleMomentum.png",
                "lvl": 7,
                "name": "Battle Momentum"
            },
            {
                "desc": "While channeling, make all nearby allied Heroes, excluding you, invulnerable. Lasts 3 seconds.",
                "img": "//d1i1jxrdh2kvwy.cloudfront.net/Images/Talents/Sanctification.png",
                "lvl": 10,
                "name": "Sanctification"
            },
            {
                "desc": "Enemies that attack you while shielded have their Attack Speed slowed by 50% and Movement Speed slowed by 50% for 2 seconds.",
                "img": "//d1i1jxrdh2kvwy.cloudfront.net/Images/Talents/ImposingWill.png",
                "lvl": 13,
                "name": "Imposing Will"
            },
            {
                "desc": "Activate to deal 10% of target enemy Hero's Max Health and heal for twice that amount.",
                "img": "//d1i1jxrdh2kvwy.cloudfront.net/Images/Talents/BloodforBlood.png",
                "lvl": 16,
                "name": "Blood for Blood"
            },
            {
                "desc": "Activate to reduce damage taken by 75% for 4 seconds.",
                "img": "//d1i1jxrdh2kvwy.cloudfront.net/Images/Talents/HardenedShield.png",
                "lvl": 20,
                "name": "Hardened Shield"
            }
        ],
        "winPercent": "69.2 %"
    },
    {
        "gamesPlayed": "23",
        "talents": [
            {
                "desc": "Collecting Regeneration Globes permanently increases Health Regeneration by 1.5 per second.",
                "img": "//d1i1jxrdh2kvwy.cloudfront.net/Images/Talents/RegenerationMaster.png",
                "lvl": 1,
                "name": "Regeneration Master"
            },
            {
                "desc": "Increases regeneration effects and all healing received by 30%.",
                "img": "//d1i1jxrdh2kvwy.cloudfront.net/Images/Talents/AmplifiedHealing.png",
                "lvl": 4,
                "name": "Amplified Healing"
            },
            {
                "desc": "Basic Attacks reduce Ability cooldowns by 0.5 seconds.",
                "img": "//d1i1jxrdh2kvwy.cloudfront.net/Images/Talents/BattleMomentum.png",
                "lvl": 7,
                "name": "Battle Momentum"
            },
            {
                "desc": "Charge target enemy Hero, dealing 60 (+8 per level) damage and stunning them for 1.5 seconds. While charging, nearby enemies are knocked back and take 30 (+4 per level) damage.",
                "img": "//d1i1jxrdh2kvwy.cloudfront.net/Images/Talents/Judgment.png",
                "lvl": 10,
                "name": "Judgment"
            },
            {
                "desc": "Deal 10 damage per second to nearby enemies.",
                "img": "//d1i1jxrdh2kvwy.cloudfront.net/Images/Talents/BurningRage.png",
                "lvl": 13,
                "name": "Burning Rage"
            },
            {
                "desc": "Activate to deal 10% of target enemy Hero's Max Health and heal for twice that amount.",
                "img": "//d1i1jxrdh2kvwy.cloudfront.net/Images/Talents/BloodforBlood.png",
                "lvl": 16,
                "name": "Blood for Blood"
            },
            {
                "desc": "Activate to reduce damage taken by 75% for 4 seconds.",
                "img": "//d1i1jxrdh2kvwy.cloudfront.net/Images/Talents/HardenedShield.png",
                "lvl": 20,
                "name": "Hardened Shield"
            }
        ],
        "winPercent": "65.2 %"
    },
    {
        "gamesPlayed": "22",
        "talents": [
            {
                "desc": "Collecting Regeneration Globes permanently increases Health Regeneration by 1.5 per second.",
                "img": "//d1i1jxrdh2kvwy.cloudfront.net/Images/Talents/RegenerationMaster.png",
                "lvl": 1,
                "name": "Regeneration Master"
            },
            {
                "desc": "Increases regeneration effects and all healing received by 30%.",
                "img": "//d1i1jxrdh2kvwy.cloudfront.net/Images/Talents/AmplifiedHealing.png",
                "lvl": 4,
                "name": "Amplified Healing"
            },
            {
                "desc": "Basic Attacks reduce Ability cooldowns by 0.5 seconds.",
                "img": "//d1i1jxrdh2kvwy.cloudfront.net/Images/Talents/BattleMomentum.png",
                "lvl": 7,
                "name": "Battle Momentum"
            },
            {
                "desc": "Charge target enemy Hero, dealing 60 (+8 per level) damage and stunning them for 1.5 seconds. While charging, nearby enemies are knocked back and take 30 (+4 per level) damage.",
                "img": "//d1i1jxrdh2kvwy.cloudfront.net/Images/Talents/Judgment.png",
                "lvl": 10,
                "name": "Judgment"
            },
            {
                "desc": "Enemies that attack you while shielded have their Attack Speed slowed by 50% and Movement Speed slowed by 50% for 2 seconds.",
                "img": "//d1i1jxrdh2kvwy.cloudfront.net/Images/Talents/ImposingWill.png",
                "lvl": 13,
                "name": "Imposing Will"
            },
            {
                "desc": "Create a ring that blocks enemies from entering the area teleported to using El'Druin's Might.",
                "img": "//d1i1jxrdh2kvwy.cloudfront.net/Images/Talents/HolyGround.png",
                "lvl": 16,
                "name": "Holy Ground"
            },
            {
                "desc": "Activate to reduce damage taken by 75% for 4 seconds.",
                "img": "//d1i1jxrdh2kvwy.cloudfront.net/Images/Talents/HardenedShield.png",
                "lvl": 20,
                "name": "Hardened Shield"
            }
        ],
        "winPercent": "59.1 %"
    },
    {
        "gamesPlayed": "14",
        "talents": [
            {
                "desc": "Smite deals 25% more damage to Heroes.",
                "img": "//d1i1jxrdh2kvwy.cloudfront.net/Images/Talents/PurgeEvil.png",
                "lvl": 1,
                "name": "Purge Evil"
            },
            {
                "desc": "Increases regeneration effects and all healing received by 30%.",
                "img": "//d1i1jxrdh2kvwy.cloudfront.net/Images/Talents/AmplifiedHealing.png",
                "lvl": 4,
                "name": "Amplified Healing"
            },
            {
                "desc": "Basic Attacks reduce Ability cooldowns by 0.5 seconds.",
                "img": "//d1i1jxrdh2kvwy.cloudfront.net/Images/Talents/BattleMomentum.png",
                "lvl": 7,
                "name": "Battle Momentum"
            },
            {
                "desc": "Charge target enemy Hero, dealing 60 (+8 per level) damage and stunning them for 1.5 seconds. While charging, nearby enemies are knocked back and take 30 (+4 per level) damage.",
                "img": "//d1i1jxrdh2kvwy.cloudfront.net/Images/Talents/Judgment.png",
                "lvl": 10,
                "name": "Judgment"
            },
            {
                "desc": "Enemies that attack you while shielded have their Attack Speed slowed by 50% and Movement Speed slowed by 50% for 2 seconds.",
                "img": "//d1i1jxrdh2kvwy.cloudfront.net/Images/Talents/ImposingWill.png",
                "lvl": 13,
                "name": "Imposing Will"
            },
            {
                "desc": "Create a ring that blocks enemies from entering the area teleported to using El'Druin's Might.",
                "img": "//d1i1jxrdh2kvwy.cloudfront.net/Images/Talents/HolyGround.png",
                "lvl": 16,
                "name": "Holy Ground"
            },
            {
                "desc": "Activate to reduce damage taken by 75% for 4 seconds.",
                "img": "//d1i1jxrdh2kvwy.cloudfront.net/Images/Talents/HardenedShield.png",
                "lvl": 20,
                "name": "Hardened Shield"
            }
        ],
        "winPercent": "57.1 %"
    },
    {
        "gamesPlayed": "28",
        "talents": [
            {
                "desc": "Smite deals 25% more damage to Heroes.",
                "img": "//d1i1jxrdh2kvwy.cloudfront.net/Images/Talents/PurgeEvil.png",
                "lvl": 1,
                "name": "Purge Evil"
            },
            {
                "desc": "Increases regeneration effects and all healing received by 30%.",
                "img": "//d1i1jxrdh2kvwy.cloudfront.net/Images/Talents/AmplifiedHealing.png",
                "lvl": 4,
                "name": "Amplified Healing"
            },
            {
                "desc": "Basic Attacks reduce Ability cooldowns by 0.5 seconds.",
                "img": "//d1i1jxrdh2kvwy.cloudfront.net/Images/Talents/BattleMomentum.png",
                "lvl": 7,
                "name": "Battle Momentum"
            },
            {
                "desc": "Charge target enemy Hero, dealing 60 (+8 per level) damage and stunning them for 1.5 seconds. While charging, nearby enemies are knocked back and take 30 (+4 per level) damage.",
                "img": "//d1i1jxrdh2kvwy.cloudfront.net/Images/Talents/Judgment.png",
                "lvl": 10,
                "name": "Judgment"
            },
            {
                "desc": "Deal 10 damage per second to nearby enemies.",
                "img": "//d1i1jxrdh2kvwy.cloudfront.net/Images/Talents/BurningRage.png",
                "lvl": 13,
                "name": "Burning Rage"
            },
            {
                "desc": "Activate to deal 10% of target enemy Hero's Max Health and heal for twice that amount.",
                "img": "//d1i1jxrdh2kvwy.cloudfront.net/Images/Talents/BloodforBlood.png",
                "lvl": 16,
                "name": "Blood for Blood"
            },
            {
                "desc": "Activate to reduce damage taken by 75% for 4 seconds.",
                "img": "//d1i1jxrdh2kvwy.cloudfront.net/Images/Talents/HardenedShield.png",
                "lvl": 20,
                "name": "Hardened Shield"
            }
        ],
        "winPercent": "50.0 %"
    }
]